bocor/__init__.py
bocor/apps.py
bocor/sitemaps.py
bocor/urls.py
bocor/views.py
bocor/static/bocor/css/style.css
bocor/static/bocor/img/footer-bg.jpg
bocor/static/bocor/js/main.js
bocor/static/bocor/scss/_footer.scss
bocor/static/bocor/scss/_general.scss
bocor/static/bocor/scss/_header.scss
bocor/static/bocor/scss/_hero.scss
bocor/static/bocor/scss/_nav.scss
bocor/static/bocor/scss/_sections.scss
bocor/static/bocor/scss/_variables.scss
bocor/static/bocor/scss/style.scss
bocor/static/bocor/vendor/aos/aos.cjs.js
bocor/static/bocor/vendor/aos/aos.css
bocor/static/bocor/vendor/aos/aos.esm.js
bocor/static/bocor/vendor/aos/aos.js
bocor/static/bocor/vendor/aos/aos.js.map
bocor/static/bocor/vendor/bootstrap/css/bootstrap-grid.css
bocor/static/bocor/vendor/bootstrap/css/bootstrap-grid.css.map
bocor/static/bocor/vendor/bootstrap/css/bootstrap-grid.min.css
bocor/static/bocor/vendor/bootstrap/css/bootstrap-grid.min.css.map
bocor/static/bocor/vendor/bootstrap/css/bootstrap-grid.rtl.css
bocor/static/bocor/vendor/bootstrap/css/bootstrap-grid.rtl.css.map
bocor/static/bocor/vendor/bootstrap/css/bootstrap-grid.rtl.min.css
bocor/static/bocor/vendor/bootstrap/css/bootstrap-grid.rtl.min.css.map
bocor/static/bocor/vendor/bootstrap/css/bootstrap-reboot.css
bocor/static/bocor/vendor/bootstrap/css/bootstrap-reboot.css.map
bocor/static/bocor/vendor/bootstrap/css/bootstrap-reboot.min.css
bocor/static/bocor/vendor/bootstrap/css/bootstrap-reboot.min.css.map
bocor/static/bocor/vendor/bootstrap/css/bootstrap-reboot.rtl.css
bocor/static/bocor/vendor/bootstrap/css/bootstrap-reboot.rtl.css.map
bocor/static/bocor/vendor/bootstrap/css/bootstrap-reboot.rtl.min.css
bocor/static/bocor/vendor/bootstrap/css/bootstrap-reboot.rtl.min.css.map
bocor/static/bocor/vendor/bootstrap/css/bootstrap-utilities.css
bocor/static/bocor/vendor/bootstrap/css/bootstrap-utilities.css.map
bocor/static/bocor/vendor/bootstrap/css/bootstrap-utilities.min.css
bocor/static/bocor/vendor/bootstrap/css/bootstrap-utilities.min.css.map
django_bocor_ds-5.0.6.dist-info/WHEEL
django_bocor_ds-5.0.6.dist-info/METADATA
django_bocor_ds-5.0.6.dist-info/RECORD
