Metadata-Version: 2.3
Name: django_bocor_ds
Version: 5.0.6
Summary: Demiansoft template(bocor)
Requires-Python: >=3.6
Requires-Dist: Django>=4.2.11
Requires-Dist: shared_lib_ds>=1.3.3
